plumb/__init__.py
plumb/base.py
plumb/memory.py
plumb/mixins.py
plumb/serializers.py
plumb/aws/__init__.py
plumb/aws/sns.py
plumb/aws/sqs.py
plumb/factories/__init__.py
plumb/kafka/__init__.py
plumb/rabbitmq/__init__.py
plumb/redis/__init__.py
plumb-1.2.5.dist-info/METADATA
plumb-1.2.5.dist-info/RECORD
plumb-1.2.5.dist-info/WHEEL
plumb-1.2.5.dist-info/top_level.txt
