Metadata-Version: 2.1
Name: plumb
Version: 1.2.5
Summary: Connect systems via many brokers such as Kafka, AWS SQS, RabbitMQ and more.
Home-page: UNKNOWN
Author: Spectro Data Engineering Team
Author-email: data-engineering@spect.ro
License: UNKNOWN
Keywords: redis,AWS,queues,distributed,kafka,RabbitMQ,AMQP
Platform: UNKNOWN
Classifier: Development Status :: 5 - Production/Stable
Classifier: License :: OSI Approved :: MIT License
Classifier: Intended Audience :: Developers
Classifier: Programming Language :: Python :: 3
Classifier: Topic :: Utilities
Classifier: Topic :: System :: Networking
Classifier: Topic :: System :: Distributed Computing
Classifier: Topic :: Software Development :: Libraries
Classifier: Topic :: Software Development :: Object Brokering
Requires-Dist: boto3 (==1.7.73)
Requires-Dist: botocore (==1.10.73)
Requires-Dist: confluent-kafka (==0.11.4)
Requires-Dist: pika (==0.12.0)
Requires-Dist: python-dateutil (==2.7.3)
Requires-Dist: redis (==2.10.6)
